{
  "100": {
    "name": "대통령실",
    "main": "정치"
  },
  "101": {
    "name": "대통령실",
    "main": "정치"
  },
  "102": {
    "name": "국회/정당",
    "main": "정치"
  },
  "103": {
    "name": "북한",
    "main": "정치"
  },
  "104": {
    "name": "행정",
    "main": "정치"
  },
  "105": {
    "name": "국방/외교",
    "main": "정치"
  },
  "106": {
    "name": "정치일반",
    "main": "정치"
  },
  "200": {
    "name": "경제",
    "main": "경제"
  },
  "201": {
    "name": "금융",
    "main": "경제"
  },
  "202": {
    "name": "증권",
    "main": "경제"
  },
  "203": {
    "name": "사회/재계",
    "main": "경제"
  },
  "204": {
    "name": "중기/벤쳐",
    "main": "경제"
  },
  "205": {
    "name": "부동산",
    "main": "경제"
  },
  "206": {
    "name": "글로벌경제",
    "main": "경제"
  },
  "207": {
    "name": "생활경제",
    "main": "경제"
  },
  "208": {
    "name": "경제일반",
    "main": "경제"
  },
  "300": {
    "name": "사회",
    "main": "사회"
  },
  "301": {
    "name": "사건사고",
    "main": "사회"
  },
  "302": {
    "name": "교육",
    "main": "사회"
  },
  "303": {
    "name": "노동",
    "main": "사회"
  },
  "304": {
    "name": "언론",
    "main": "사회"
  },
  "305": {
    "name": "환경",
    "main": "사회"
  },
  "306": {
    "name": "인권/복지",
    "main": "사회"
  },
  "307": {
    "name": "식품의료",
    "main": "사회"
  },
  "308": {
    "name": "사회일반",
    "main": "사회"
  },
  "400": {
    "name": "IT/과학",
    "main": "IT/과학"
  },
  "401": {
    "name": "사건사고",
    "main": "IT/과학"
  },
  "402": {
    "name": "교육",
    "main": "IT/과학"
  },
  "403": {
    "name": "노동",
    "main": "IT/과학"
  },
  "404": {
    "name": "언론",
    "main": "IT/과학"
  },
  "405": {
    "name": "환경",
    "main": "IT/과학"
  },
  "406": {
    "name": "인권/복지",
    "main": "IT/과학"
  },
  "407": {
    "name": "식품의료",
    "main": "IT/과학"
  },
  "408": {
    "name": "사회일반",
    "main": "IT/과학"
  },
  "500": {
    "name": "세계",
    "main": "세계"
  },
  "501": {
    "name": "사건사고",
    "main": "세계"
  },
  "502": {
    "name": "교육",
    "main": "세계"
  },
  "503": {
    "name": "노동",
    "main": "세계"
  },
  "504": {
    "name": "언론",
    "main": "세계"
  },
  "505": {
    "name": "환경",
    "main": "세계"
  },
  "506": {
    "name": "인권/복지",
    "main": "세계"
  },
  "507": {
    "name": "식품의료",
    "main": "세계"
  },
  "508": {
    "name": "사회일반",
    "main": "세계"
  }
}
